mov_cli_files/__init__.py
mov_cli_files/paths.py
mov_cli_files/scraper.py
mov_cli_files-1.1.1.dist-info/LICENSE
mov_cli_files-1.1.1.dist-info/METADATA
mov_cli_files-1.1.1.dist-info/WHEEL
mov_cli_files-1.1.1.dist-info/top_level.txt
mov_cli_files-1.1.1.dist-info/RECORD
