Metadata-Version: 2.1
Name: mov-cli-files
Version: 1.1.1
Summary: A mov-cli v4 plugin for watching files on your device.
Author-email: Ananas <ananas@r3tr0ananas.pro>
License: MIT License
Project-URL: GitHub, https://github.com/mov-cli/mov-cli-files
Project-URL: BugTracker, https://github.com/mov-cli/mov-cli-files/issues
Keywords: amazing mov-cli plugin
Classifier: Operating System :: Microsoft :: Windows :: Windows 11
Classifier: Operating System :: Microsoft :: Windows :: Windows 10
Classifier: Operating System :: POSIX :: Linux
Classifier: License :: OSI Approved :: MIT License
Classifier: Programming Language :: Python :: 3.8
Classifier: Programming Language :: Python :: 3.9
Classifier: Programming Language :: Python :: 3.10
Classifier: Programming Language :: Python :: 3.11
Classifier: Programming Language :: Python :: 3.12
Requires-Python: >=3.8
License-File: LICENSE
Requires-Dist: thefuzz
Requires-Dist: mov-cli >=4.3.14
Provides-Extra: dev
Requires-Dist: ruff ; extra == 'dev'
Requires-Dist: build ; extra == 'dev'
